cs224_lab5/seq_10101_test.v
`timescale 1ns / 1ps

////////////////////////////////////////////////////////////////////////////////
// Company: 
// Engineer:
//
// Create Date:   17:37:26 02/08/2022
// Design Name:   seq_10101
// Module Name:   C:/cs221_lab/cs224_lab5/seq_10101_test.v
// Project Name:  cs224_lab5
// Target Device:  
// Tool versions:  
// Description: 
//
// Verilog Test Fixture created by ISE for module: seq_10101
//
// Dependencies:
// 
// Revision:
// Revision 0.01 - File Created
// Additional Comments:
// 
////////////////////////////////////////////////////////////////////////////////

// Code your design here
module seq_10101(output reg out, input xin, clk, rst);
  parameter s0 = 3'b000;
  parameter s1 = 3'b001;
  parameter s2 = 3'b010;
  parameter s3 = 3'b011;
  parameter s4 = 3'b100;
  parameter s5 = 3'b101;
  
  reg [2:0] nextstate;
  reg [2:0] state;
  
  always @ (posedge clk,negedge rst)
    begin
      if(!rst) state <= s0;
      else state <= nextstate;
    end
  
  
  always @(state, xin)
    case(state)
      s0: begin
        if(xin) nextstate = s1;
        else nextstate = s0;
      end
      s1: begin
        if(xin) nextstate = s1;
        else nextstate = s2;
      end
      s2: begin
        if(xin) nextstate = s3;
        else nextstate = s0;
      end
      s3: begin
        if(xin) nextstate = s1;
        else nextstate = s4;
      end
      s4: begin
        if(xin) nextstate = s5;
        else nextstate = s0;
      end
      s5: begin
        if(xin) nextstate = s1;
        else nextstate = s0;
      end
    endcase
  
  always @(state)
    case(state)
      s0, s1, s2, s3, s4: out <= 1'b0;
      s5: out <= 1'b1;
    endcase
  
endmodule

cs224_lab5/t_seq_10101.v
`timescale 1ns / 1ps

////////////////////////////////////////////////////////////////////////////////
// Company: 
// Engineer:
//
// Create Date:   17:41:48 02/08/2022
// Design Name:   seq_10101
// Module Name:   C:/cs221_lab/cs224_lab5/t_seq_10101.v
// Project Name:  cs224_lab5
// Target Device:  
// Tool versions:  
// Description: 
//
// Verilog Test Fixture created by ISE for module: seq_10101
//
// Dependencies:
// 
// Revision:
// Revision 0.01 - File Created
// Additional Comments:
// 
////////////////////////////////////////////////////////////////////////////////

module t_seq_10101;
  wire t_out;
  reg t_xin, t_clk, t_rst;
  
  seq_10101 M2(t_out, t_xin, t_clk, t_rst);
  
  initial begin
    $dumpfile("dump.vcd");
    $dumpvars(0,M2);
  end
  
  initial t_clk = 1'b0;
  always #5 t_clk = !t_clk;
  
  initial begin
    t_rst = 1'b0;
    #5 t_rst = 1'b1;
  end
  
  initial begin
    #5  t_xin = 1'b0;
    #10 t_xin = 1'b0;
    #10 t_xin = 1'b1;
    #10 t_xin = 1'b1; t_rst = 1'b1;
    #10 t_xin = 1'b0;
    #10 t_xin = 1'b1;
    #10 t_xin = 1'b0; t_rst = 1'b0;
    #10 t_xin = 1'b1; 
    #10 t_xin = 1'b1;
    #10 t_xin = 1'b0;
    #10 t_xin = 1'b1;
    #10 t_xin = 1'b1;
    #10 t_xin = 1'b0;
    #10 t_xin = 1'b1;
    #10 t_xin = 1'b0;
    #10 t_xin = 1'b1;
    #10 t_xin = 1'b0;
    #10 t_xin = 1'b1;
    #10 t_xin = 1'b1;
    #20 $finish;
  end
  
  initial begin   
    #5 $display($time,, "%b   %b",t_xin, t_out);
    repeat(25) begin  
      #10 $display($time,, "%b   %b", t_xin, t_out);   
    end   
  end
  
endmodule

cs224_lab5/dump.vcd
$date
   Tue Feb 08 18:15:52 2022
$end
$version
  P.40xd
$end
$timescale
  1ps
$end
$scope module t_seq_10101 $end
$scope module M2 $end
$var wire 1 ! xin $end
$var wire 1 " clk $end
$var wire 1 # rst $end
$var reg 1 $ out $end
$var reg 3 % nextstate [2:0] $end
$var reg 3 & state [2:0] $end
$upscope $end
$upscope $end
$enddefinitions $end
#0
$dumpvars
0#
x$
bx %
bx &
x!
0"
$end
#5000
1#
0$
b0 %
b0 &
0!
1"
#10000
0"
#15000
1"
#20000
0"
#25000
b1 %
1!
1"
#30000
0"
#35000
1"
#40000
0"
#45000
b0 %
0!
1"
#50000
0"
#55000
b1 %
1!
1"
#60000
0"
#65000
0#
b0 %
0!
1"
#70000
0"
#75000
b1 %
b1 &
1!
1"
#80000
0"
#85000
1"
#90000
0"
#95000
b0 %
b10 &
0!
1"
#100000
0"
#105000
b1 %
b11 &
1!
1"
#110000
0"
#115000
b1 &
1"
#120000
0"
#125000
b0 %
b10 &
0!
1"
#130000
0"
#135000
b1 %
b11 &
1!
1"
#140000
0"
#145000
b0 %
b100 &
0!
1"
#150000
0"
#155000
1$
b1 %
b101 &
1!
1"
#160000
0"
#165000
0$
b0 %
b0 &
0!
1"
#170000
0"
#175000
b1 %
b1 &
1!
1"
